touketsu/__init__.py
touketsu/core.py
touketsu/utils.py
touketsu-0.1.1.dist-info/LICENSE
touketsu-0.1.1.dist-info/METADATA
touketsu-0.1.1.dist-info/WHEEL
touketsu-0.1.1.dist-info/top_level.txt
touketsu-0.1.1.dist-info/RECORD
