Metadata-Version: 2.1
Name: touketsu
Version: 0.1.1
Summary: A package for creating classes that disallow dynamic attribute creation.
Home-page: https://github.com/phetdam/touketsu
Author: Derek Huang
Author-email: djh458@stern.nyu.edu
License: MIT
Project-URL: Documentation, https://touketsu.readthedocs.io/en/latest/
Project-URL: Source, https://github.com/phetdam/touketsu/
Platform: UNKNOWN
Classifier: License :: OSI Approved :: MIT License
Classifier: Operating System :: OS Independent
Classifier: Programming Language :: Python :: 3.6
Classifier: Programming Language :: Python :: 3.7
Classifier: Programming Language :: Python :: 3.8
Requires-Python: >=3.6
